medImgProc/GUI.py
medImgProc/__init__.py
medImgProc/image.py
medImgProc/interpolationScheme.py
medImgProc/pointSpeckleProc.py
medImgProc/processFunc.py
medImgProc-2.7.4.dist-info/LICENSE
medImgProc-2.7.4.dist-info/METADATA
medImgProc-2.7.4.dist-info/WHEEL
medImgProc-2.7.4.dist-info/top_level.txt
medImgProc-2.7.4.dist-info/RECORD
