Metadata-Version: 2.1
Name: medImgProc
Version: 2.7.4
Summary: Medical Image Processing module for viewing and editing.
Home-page: https://github.com/WeiXuanChan/medImgProc
Author: Wei Xuan Chan
Author-email: w.x.chan1986@gmail.com
License: MIT
Download-URL: https://github.com/WeiXuanChan/medImgProc/archive/v2.7.4.tar.gz
Keywords: medical,image
Platform: UNKNOWN
Classifier: Development Status :: 5 - Production/Stable
Classifier: Intended Audience :: Developers
Classifier: Topic :: Software Development :: Build Tools
Classifier: License :: OSI Approved :: MIT License
Classifier: Programming Language :: Python :: 3.6
Classifier: Programming Language :: Python :: 3.7
Requires-Dist: numpy
Requires-Dist: matplotlib
Requires-Dist: imageio
Requires-Dist: scipy
Requires-Dist: trimesh
Provides-Extra: auto_read_dimlen_in_imread
Requires-Dist: medpy ; extra == 'auto_read_dimlen_in_imread'
